{"moduleName":null,"summaries":[{"symbol":{"__symbol":0,"members":[]},"metadata":{"__symbolic":"class","members":{"__ctor__":[{"__symbolic":"constructor","parameters":[{"__symbolic":"resolved","symbol":{"__symbol":1,"members":[]},"line":10,"character":30,"fileName":"C:/Users/splik/Desktop/Projects/Single-Page-App-Angular2-Nodejs/assets/app/user-auth/userauth.service.ts"},{"__symbolic":"resolved","symbol":{"__symbol":2,"members":[]},"line":10,"character":58,"fileName":"C:/Users/splik/Desktop/Projects/Single-Page-App-Angular2-Nodejs/assets/app/user-auth/userauth.service.ts"}]}],"signup":[{"__symbolic":"method"}],"signin":[{"__symbolic":"method"}],"logout":[{"__symbolic":"method"}],"isLoggedIn":[{"__symbolic":"method"}]}},"type":{"summaryKind":3,"type":{"reference":{"__symbol":0,"members":[]},"diDeps":[{"isAttribute":false,"isHost":false,"isSelf":false,"isSkipSelf":false,"isOptional":false,"token":{"identifier":{"reference":{"__symbol":1,"members":[]}}}},{"isAttribute":false,"isHost":false,"isSelf":false,"isSkipSelf":false,"isOptional":false,"token":{"identifier":{"reference":{"__symbol":2,"members":[]}}}}],"lifecycleHooks":[]}}}],"symbols":[{"__symbol":0,"name":"AuthService","filePath":"./userauth.service"},{"__symbol":1,"name":"Http","filePath":"@angular/http/http"},{"__symbol":2,"name":"ErrorService","filePath":"../user-errors/usererrors.service"}]}